[
    {
        "name": "Contract parrot-final version.jpg",
        "path": "/images/media-1680197706533-401116180.jpeg",
        "id": 1,
        "dateCreated": "2023-03-30T17:35:06.534Z"
    },
    {
        "name": "butterflies_SampleJPGImage_500kbmb.jpg",
        "path": "/images/media-1680197715190-999088358.jpeg",
        "id": 2,
        "dateCreated": "2023-03-30T17:35:15.196Z"
    },
    {
        "name": "SampleJPGImage_1mbmb.jpg",
        "path": "/images/media-1680197725588-106732009.jpeg",
        "id": 4,
        "dateCreated": "2023-03-30T17:35:25.596Z"
    },
    {
        "name": "deadpool.jpeg",
        "path": "/images/media-1680199284201-998472927.jpeg",
        "id": 5,
        "dateCreated": "2023-03-30T18:01:24.201Z"
    }
]